MANIFEST.in
README.md
setup.cfg
setup.py
hy_kernel/__init__.py
hy_kernel/hy_kernel.py
hy_kernel/hy_setup.py
hy_kernel/version.py
hy_kernel.egg-info/PKG-INFO
hy_kernel.egg-info/SOURCES.txt
hy_kernel.egg-info/dependency_links.txt
hy_kernel.egg-info/requires.txt
hy_kernel.egg-info/top_level.txt
hy_kernel/assets/kernel.js
hy_kernel/assets/kernel.json
hy_kernel/assets/logo-32x32.png
hy_kernel/assets/logo-64x64.png
hy_kernel/tests/__init__.py
hy_kernel/tests/test_input.py
hy_kernel/tests/test_notebook.py