Metadata-Version: 1.1
Name: hy-kernel
Version: 0.3.0
Summary: A hy kernel for IPython
Home-page: https://github.com/bollwyvl/hy_kernel
Author: Nicholas Bollweg
Author-email: nick.bollweg@gmail.com
License: UNKNOWN
Platform: UNKNOWN
Classifier: Framework :: IPython
Classifier: License :: OSI Approved :: BSD License
Classifier: Programming Language :: Python :: 3
Classifier: Programming Language :: Python :: 2
Classifier: Programming Language :: Lisp
